muo_core.v
module mu0_core (
    input clk,
    input reset,
    output reg [15:0] acc

);
// Here is where i will write all of my logic 

    reg [11:0] pc;
    reg [15:0] ir;
    reg [15:0] memory [0:255]; // 256 16-bit words of memory


endmodule

tb/mu0_tb.v
`timescale 1ns / 1ps // This is a verilog compiler directive that sets the time unit and precision of the file 
// All delay values like #5 or #200 are interpreted in nanoseconds so these values mean 5 nanosecondds or 200 nanoseconds respectively 

// 1ps represents the time precision that the simulator uses internally. Times are rounded to the nearest picosecond

module mu0_core_tb;

    // Inputs
    reg clk;
    reg reset;

    // Outputs
    wire [15:0] acc;

    /**
    * This creates an instance of my mu0_core.v module
    * the name of the instance is uut
    */
    mu0_core uut (
        .clk(clk),
        .reset(reset),
        .acc(acc)
    );

    /**
    * Clock generation
    * The line always in the test bench essentially means repeat this forever during the duration of the simulation
    * This line of code is saying every 5 nanoseconds flip the clock, 5 ns high + 5 ns low (10 ns period clock)
    */ 
    always #5 clk = ~clk;

    /* Main test
    *
    *
    *
    */

    initial begin
        $dumpfile("sim/dump.vcd"); // This means create a file inside the sim folder called  dump.vcd, this file will contain all the signal changes during the simulation
        $dumpvars(0, mu0_core_tb); // This means start recording all the signals under mu0_core_tb into that file, 0 means include this module and everything inside it 

        // initialise inputs
        clk = 0;
        reset = 1;
        #10 reset = 0;
        // run your test
        // stop simulation
        #200 $finish;
    end

    /*
    * Monitor outputs:
    * This is for printing values to the simulator console whenever they change
    * $monitor(...): This sets up a continuous print any time any of the values in the argument list changes 
    */ 
    initial begin
        $monitor("Time=%0t acc=%0d", $time, acc); 
    end

endmodule

sim/dump.vcd
$date
	Mon Mar 16 14:16:51 2026
$end
$version
	Icarus Verilog
$end
$timescale
	1ps
$end
$scope module mu0_core_tb $end
$var wire 16 ! acc [15:0] $end
$var reg 1 " clk $end
$var reg 1 # reset $end
$scope module uut $end
$var wire 1 " clk $end
$var wire 1 # reset $end
$var reg 16 $ acc [15:0] $end
$var reg 16 % ir [15:0] $end
$var reg 12 & pc [11:0] $end
$upscope $end
$upscope $end
$enddefinitions $end
$comment Show the parameter values. $end
$dumpall
$end
#0
$dumpvars
b0 &
b0 %
b0 $
1#
0"
b0 !
$end
#5000
1"
#10000
0"
0#
#15000
b10000 !
b10000 $
b1 &
b10000 %
1"
#20000
0"
#25000
b101 !
b101 $
b10 &
b10000000010001 %
1"
#30000
0"
#35000
b1010 !
b1010 $
b11 &
b1000000010010 %
1"
#40000
0"
#45000
b100 &
b1111000000000000 %
1"
#50000
0"
#55000
b100 &
bx %
1"
#60000
0"
#65000
b101 &
1"
#70000
0"
#75000
b110 &
1"
#80000
0"
#85000
b111 &
1"
#90000
0"
#95000
b1000 &
1"
#100000
0"
#105000
b1001 &
1"
#110000
0"
#115000
b1010 &
1"
#120000
0"
#125000
b1011 &
1"
#130000
0"
#135000
b1100 &
1"
#140000
0"
#145000
b1101 &
1"
#150000
0"
#155000
b1110 &
1"
#160000
0"
#165000
b1111 &
1"
#170000
0"
#175000
b10000 &
1"
#180000
0"
#185000
b10001 &
b101 %
1"
#190000
0"
#195000
bx !
bx $
b10010 &
1"
#200000
0"
#205000
b10011 &
b1010 %
1"
