src/mu0_core.v
module mu0_core (
    input clk,
    input reset,
    output reg [15:0] acc

);
// Here is where i will write all of my logic 

    reg [11:0] pc;
    reg [15:0] ir;
    reg fetch; // If high then you perform a fetch, else you perform an execute 
    reg [15:0] memory [0:255]; // 256 16-bit words of memory
    

    initial begin
        // Program
        memory[0] = 16'h0010; // LDA 16 → load value at address 16
        memory[1] = 16'h2011; // ADD 17 → add value at address 17
        memory[2] = 16'h1012; // STO 18 → store result at address 18
        memory[3] = 16'hF000; // STP    → halt
    
        // Data
        memory[16] = 16'h0005; // value 5
        memory[17] = 16'h0005; // value 5
    end

    always @(posedge clk or posedge reset)
        begin
            // if reset is high that means we set the pc, ir and the acc to 0
            if (reset)
                begin 
                    pc <= 0;
                    ir <= 0;
                    acc <= 0;
                    fetch <= 1;
                end
            else
                begin
                        // Load what ever is at address pc into the 
                    if (fetch)
                        begin
                            ir <= memory[pc];
                            fetch <= 0;
                        end 

                    else
                        begin
                        // Point the pc to the next instruction
                        pc <= pc + 1;
                        case (ir[15:12])
                            4'h0: // LDA, load the value from [11:0] in the accumulator 
                                begin
                                    acc <= memory[ir[11:0]];
                                end 

                            4'h1: // STO, stores the value in the accumulator into that memory address
                                begin 
                                    memory[ir[11:0]] <= acc;
                                end 
                                
                            4'h2: // ADD, acc = acc + memory[ir[11:0]] 
                                begin 
                                    acc <= acc + memory[ir[11:0]];
                                end 

                            4'h3: // SUB, acc = acc - memory[operand]
                                begin 
                                    acc <= acc - memory[ir[11:0]];
                                end 
                            4'h4: // JMP, pc = operand
                                begin
                                    pc <= ir[11:0];

                                end
                            4'h5: // JGE, if acc >= 0, pc = operand
                                begin
                                    if (acc[15] == 0)
                                        begin 
                                            pc <= ir[11:0];
                                        end
                                end
                                    
                            4'h6: // JNE, if acc != 0, pc = operand
                                begin 
                                    if (acc != 0)
                                        begin
                                            pc <= ir[11:0];
                                        end

                                end 
                            4'hF: // STP, halt, do nothing
                                begin
                                    pc <= pc;
                                end
                            
                        endcase
                        fetch <= 1;
                        end
                end
            end

endmodule

tb/mu0_tb.v
`timescale 1ns / 1ps // This is a verilog compiler directive that sets the time unit and precision of the file 
// All delay values like #5 or #200 are interpreted in nanoseconds so these values mean 5 nanosecondds or 200 nanoseconds respectively 

// 1ps represents the time precision that the simulator uses internally. Times are rounded to the nearest picosecond

module mu0_core_tb;

    // Inputs
    reg clk;
    reg reset;

    // Outputs
    wire [15:0] acc;

    /**
    * This creates an instance of my mu0_core.v module
    * the name of the instance is uut
    */
    mu0_core uut (
        .clk(clk),
        .reset(reset),
        .acc(acc)
    );

    /**
    * Clock generation
    * The line always in the test bench essentially means repeat this forever during the duration of the simulation
    * This line of code is saying every 5 nanoseconds flip the clock, 5 ns high + 5 ns low (10 ns period clock)
    */ 
    always #5 clk = ~clk;

    /* Main test
    *
    *
    *
    */

    initial begin
        $dumpfile("sim/dump.vcd"); // This means create a file inside the sim folder called  dump.vcd, this file will contain all the signal changes during the simulation
        $dumpvars(0, mu0_core_tb); // This means start recording all the signals under mu0_core_tb into that file, 0 means include this module and everything inside it 

        // initialise inputs
        clk = 0;
        reset = 1;
        #10 reset = 0;
        // run your test
        // stop simulation
        #200 $finish;
    end

    /*
    * Monitor outputs:
    * This is for printing values to the simulator console whenever they change
    * $monitor(...): This sets up a continuous print any time any of the values in the argument list changes 
    */ 
    initial begin
        $monitor("Time=%0t acc=%0d", $time, acc); 
    end

endmodule

sim/dump.vcd
$date
	Mon Mar 16 15:46:17 2026
$end
$version
	Icarus Verilog
$end
$timescale
	1ps
$end
$scope module mu0_core_tb $end
$var wire 16 ! acc [15:0] $end
$var reg 1 " clk $end
$var reg 1 # reset $end
$scope module uut $end
$var wire 1 " clk $end
$var wire 1 # reset $end
$var reg 16 $ acc [15:0] $end
$var reg 1 % fetch $end
$var reg 16 & ir [15:0] $end
$var reg 12 ' pc [11:0] $end
$upscope $end
$upscope $end
$enddefinitions $end
$comment Show the parameter values. $end
$dumpall
$end
#0
$dumpvars
b0 '
b0 &
1%
b0 $
1#
0"
b0 !
$end
#5000
1"
#10000
0"
0#
#15000
0%
b10000 &
1"
#20000
0"
#25000
1%
b101 !
b101 $
b1 '
1"
#30000
0"
#35000
0%
b10000000010001 &
1"
#40000
0"
#45000
1%
b1010 !
b1010 $
b10 '
1"
#50000
0"
#55000
0%
b1000000010010 &
1"
#60000
0"
#65000
1%
b11 '
1"
#70000
0"
#75000
0%
b1111000000000000 &
1"
#80000
0"
#85000
1%
b11 '
1"
#90000
0"
#95000
0%
1"
#100000
0"
#105000
1%
b11 '
1"
#110000
0"
#115000
0%
1"
#120000
0"
#125000
1%
b11 '
1"
#130000
0"
#135000
0%
1"
#140000
0"
#145000
1%
b11 '
1"
#150000
0"
#155000
0%
1"
#160000
0"
#165000
1%
b11 '
1"
#170000
0"
#175000
0%
1"
#180000
0"
#185000
1%
b11 '
1"
#190000
0"
#195000
0%
1"
#200000
0"
#205000
1%
b11 '
1"
